richframe/__init__.py
richframe/api.py
richframe/core/__init__.py
richframe/core/builder.py
richframe/core/model.py
richframe/format/__init__.py
richframe/format/formatter.py
richframe/format/numbers.py
richframe/format/resolver.py
richframe/format/temporal.py
richframe/io/pandas_adapter.py
richframe/layout/__init__.py
richframe/layout/column.py
richframe/layout/filtering.py
richframe/layout/table.py
richframe/merge/__init__.py
richframe/merge/engine.py
richframe/plugins/__init__.py
richframe/plugins/base.py
richframe/plugins/color.py
richframe/plugins/databar.py
richframe/plugins/icon.py
richframe/plugins/rules.py
richframe/py.typed
richframe/render/__init__.py
richframe/render/html_renderer.py
richframe/style/__init__.py
richframe/style/model.py
richframe/style/registry.py
richframe/style/theme.py
richframe/templates/__init__.py
richframe/templates/table.html.j2
richframe-0.3.0.dist-info/WHEEL
richframe-0.3.0.dist-info/METADATA
richframe-0.3.0.dist-info/RECORD
