Metadata-Version: 2.3
Name: richframe
Version: 0.3.0
Summary: A library for rendering rich HTML tables from pandas DataFrames.
Keywords: pandas,dataframe,html,tables,styling,formatting
Author: Kunal Kaul
Author-email: Kunal Kaul <kkdevcode@gmail.com>
License:                                  Apache License
Classifier: Development Status :: 3 - Alpha
Classifier: Intended Audience :: Developers
Classifier: License :: OSI Approved :: Apache Software License
Classifier: Programming Language :: Python
Classifier: Programming Language :: Python :: 3
Classifier: Programming Language :: Python :: 3.12
Classifier: Topic :: Software Development :: Libraries
Classifier: Topic :: Utilities
Requires-Dist: pandas>=2.1,<3
Requires-Dist: jinja2>=3.1,<4
Requires-Dist: babel>=2.14,<3 ; extra == 'locale'
Requires-Python: >=3.12
Project-URL: Documentation, https://github.com/kunalkaul/richframe#readme
Project-URL: Homepage, https://github.com/kunalkaul/richframe
Project-URL: Issues, https://github.com/kunalkaul/richframe/issues
Project-URL: Source, https://github.com/kunalkaul/richframe
Provides-Extra: locale
